__init__.py
EInvoiceTWSDK/__init__.py
EInvoiceTWSDK/api.py
EInvoiceTWSDK/client.py
EInvoiceTWSDK/exceptions.py
EInvoiceTWSDK/subscriber.py
EInvoiceTWSDK/utils.py
EInvoiceTWSDK/__pycache__/__init__.cpython-37.pyc
EInvoiceTWSDK/__pycache__/api.cpython-37.pyc
EInvoiceTWSDK/__pycache__/client.cpython-37.pyc
EInvoiceTWSDK/__pycache__/exceptions.cpython-37.pyc
__pycache__/__init__.cpython-37.pyc
build/__init__.py
build/lib/__init__.py
build/lib/EInvoiceTWSDK/__init__.py
build/lib/EInvoiceTWSDK/api.py
build/lib/EInvoiceTWSDK/client.py
build/lib/EInvoiceTWSDK/exceptions.py
build/lib/EInvoiceTWSDK/subscriber.py
build/lib/EInvoiceTWSDK/utils.py
build/lib/build/__init__.py
build/lib/build/lib/__init__.py
build/lib/build/lib/EInvoiceTWSDK/__init__.py
build/lib/build/lib/EInvoiceTWSDK/api.py
build/lib/build/lib/EInvoiceTWSDK/client.py
build/lib/build/lib/EInvoiceTWSDK/exceptions.py
build/lib/build/lib/EInvoiceTWSDK/subscriber.py
build/lib/build/lib/EInvoiceTWSDK/utils.py
build/lib/build/lib/build/__init__.py
build/lib/build/lib/build/lib/__init__.py
build/lib/build/lib/build/lib/EInvoiceTWSDK/__init__.py
build/lib/build/lib/build/lib/EInvoiceTWSDK/api.py
build/lib/build/lib/build/lib/EInvoiceTWSDK/client.py
build/lib/build/lib/build/lib/EInvoiceTWSDK/exceptions.py
build/lib/build/lib/build/lib/EInvoiceTWSDK/subscriber.py
build/lib/build/lib/build/lib/EInvoiceTWSDK/utils.py
build/lib/build/lib/build/lib/build/__init__.py
build/lib/build/lib/build/lib/build/lib/__init__.py
build/lib/build/lib/build/lib/build/lib/EInvoiceTWSDK/__init__.py
build/lib/build/lib/build/lib/build/lib/EInvoiceTWSDK/api.py
build/lib/build/lib/build/lib/build/lib/EInvoiceTWSDK/client.py
build/lib/build/lib/build/lib/build/lib/EInvoiceTWSDK/exceptions.py
build/lib/build/lib/build/lib/build/lib/EInvoiceTWSDK/subscriber.py
build/lib/build/lib/build/lib/build/lib/EInvoiceTWSDK/utils.py
build/lib/build/lib/build/lib/build/lib/build/__init__.py
build/lib/build/lib/build/lib/build/lib/build/lib/__init__.py
EInvoiceTWSDK-0.0.2.dist-info/METADATA
EInvoiceTWSDK-0.0.2.dist-info/WHEEL
EInvoiceTWSDK-0.0.2.dist-info/top_level.txt
EInvoiceTWSDK-0.0.2.dist-info/RECORD
