Metadata-Version: 2.1
Name: EInvoiceTWSDK
Version: 0.0.2
Summary: python SDK for taiwan e-invoice
Home-page: UNKNOWN
Author: Ben
Author-email: UNKNOWN
License: MIT License
Keywords: EInvoiceTWSDK
Platform: any
Requires-Dist: future (>=0.18.2)
Requires-Dist: requests (>=2.23.0)
